pycounts_khalidca/__init__.py
pycounts_khalidca/plotting.py
pycounts_khalidca/pycounts.py
pycounts_khalidca-0.1.0.dist-info/LICENSE
pycounts_khalidca-0.1.0.dist-info/WHEEL
pycounts_khalidca-0.1.0.dist-info/METADATA
pycounts_khalidca-0.1.0.dist-info/RECORD
